odoo/addons/stock_inventory_justification/README.rst
odoo/addons/stock_inventory_justification/__init__.py
odoo/addons/stock_inventory_justification/__manifest__.py
odoo/addons/stock_inventory_justification/i18n/stock_inventory_justification.pot
odoo/addons/stock_inventory_justification/models/__init__.py
odoo/addons/stock_inventory_justification/models/stock_inventory.py
odoo/addons/stock_inventory_justification/models/stock_inventory_justification.py
odoo/addons/stock_inventory_justification/readme/CONTRIBUTORS.rst
odoo/addons/stock_inventory_justification/readme/DESCRIPTION.rst
odoo/addons/stock_inventory_justification/readme/USAGE.rst
odoo/addons/stock_inventory_justification/security/security.xml
odoo/addons/stock_inventory_justification/static/description/icon.png
odoo/addons/stock_inventory_justification/static/description/index.html
odoo/addons/stock_inventory_justification/views/stock_inventory.xml
odoo/addons/stock_inventory_justification/views/stock_inventory_justification.xml
odoo13_addon_stock_inventory_justification-13.0.1.0.1.dev4.dist-info/METADATA
odoo13_addon_stock_inventory_justification-13.0.1.0.1.dev4.dist-info/WHEEL
odoo13_addon_stock_inventory_justification-13.0.1.0.1.dev4.dist-info/top_level.txt
odoo13_addon_stock_inventory_justification-13.0.1.0.1.dev4.dist-info/RECORD
